pyblast/__bin__.py
pyblast/__init__.py
pyblast/__version__.py
pyblast/blast/__init__.py
pyblast/blast/bioblastfactory.py
pyblast/blast/blast.py
pyblast/blast/blast_parser.py
pyblast/blast/json_parser.py
pyblast/blast/seqdb.py
pyblast/cli.py
pyblast/constants.py
pyblast/exceptions.py
pyblast/log.py
pyblast/utils/__init__.py
pyblast/utils/cmd.py
pyblast/utils/span.py
pyblastbio-0.9.dist-info/entry_points.txt
pyblastbio-0.9.dist-info/LICENSE.txt
pyblastbio-0.9.dist-info/WHEEL
pyblastbio-0.9.dist-info/METADATA
pyblastbio-0.9.dist-info/RECORD
