Metadata-Version: 2.1
Name: pyblastbio
Version: 0.9
Summary: 
Home-page: https://www.github.com/jvrana/pyblast2
Author: Justin Vrana
Author-email: justin.vrana@gmail.com
Requires-Python: >=3.6,<4.0
Classifier: Programming Language :: Python :: 3
Classifier: Programming Language :: Python :: 3.6
Classifier: Programming Language :: Python :: 3.7
Classifier: Programming Language :: Python :: 3.8
Provides-Extra: testing
Requires-Dist: biopython (>=1.73,<2.0)
Requires-Dist: fire (>=0.3,<0.4)
Requires-Dist: loggable-jdv (>=0.1.4,<0.2.0)
Requires-Dist: networkx (>=2.4,<3.0)
Requires-Dist: termcolor (>=1.1,<2.0)
Requires-Dist: tox (>=3.13,<4.0); extra == "testing"
Requires-Dist: tox-conda (>=0.2.0,<0.3.0); extra == "testing"
Project-URL: Documentation, https://www.github.com/jvrana/pyblast2
Project-URL: Repository, https://www.github.com/jvrana/pyblast2
